[
    {
        "website": "http://kpi.go.id/"
    },
    {
        "website": "https://jabarprov.go.id/"
    },
    {
        "website": "https://rembangkab.go.id/"
    },
    {
        "website": "https://kemlu.go.id/"
    },
    {
        "website": "https://pemkomedan.go.id/"
    },
    {
        "website": "https://indonesia.go.id/"
    },
    {
        "website": "http://lipi.go.id/"
    },
    {
        "website": "https://bnn.go.id/"
    },
    {
        "website": "https://ombudsman.go.id/"
    },
    {
        "website": "https://madiunkab.go.id/"
    },
    {
        "website": "https://bssn.go.id/"
    },
    {
        "website": "https://solokkota.go.id/"
    },
    {
        "website": "https://bogorkab.go.id/"
    },
    {
        "website": "http://mataramkota.go.id/"
    },
    {
        "website": "https://ahu.go.id/"
    },
    {
        "website": "https://dikti.kemdikbud.go.id/"
    },
    {
        "website": "https://lpjk.pu.go.id/"
    },
    {
        "website": "http://dpmptsp.sumbarprov.go.id/"
    },
    {
        "website": "https://pddikti.kemdikbud.go.id/"
    },
    {
        "website": "http://disperindag.jatengprov.go.id/"
    },
    {
        "website": "http://www.bekasikab.go.id/"
    },
    {
        "website": "https://pikobar.jabarprov.go.id/"
    },
    {
        "website": "http://www.bappebti.go.id/"
    },
    {
        "website": "https://digitalent.kominfo.go.id/"
    },
    {
        "website": "https://bpipi.kemenperin.go.id/"
    },
    {
        "website": "https://www.menpan.go.id/"
    },
    {
        "website": "https://siapdol.sumedangkab.go.id/"
    },
    {
        "website": "https://www.subang.go.id/"
    },
    {
        "website": "https://bkd.sulbarprov.go.id/"
    },
    {
        "website": "https://bkd.jabarprov.go.id/"
    },
    {
        "website": "https://disdukcapil.lampungutarakab.go.id/"
    },
    {
        "website": "https://dispendukcapil.surabaya.go.id/"
    },
    {
        "website": "https://bapenda.jabarprov.go.id/"
    },
    {
        "website": "https://www.dpr.go.id/"
    },
    {
        "website": "https://www.mtbkab.go.id/"
    },
    {
        "website": "https://www.kemenag.go.id/"
    },
    {
        "website": "https://jatengprov.go.id/"
    },
    {
        "website": "https://aceh.bkn.go.id/"
    },
    {
        "website": "https://ppdb.jakarta.go.id/"
    },
    {
        "website": "https://edukcapil.karawangkab.go.id/"
    },
    {
        "website": "https://sipenduduk.pekanbaru.go.id/"
    },
    {
        "website": "https://emis.kemenag.go.id/"
    },
    {
        "website": "https://dtks.kemensos.go.id/"
    },
    {
        "website": "https://karirhub.kemnaker.go.id/"
    },
    {
        "website": "https://www.komnasham.go.id/"
    },
    {
        "website": "https://infocorona.baliprov.go.id/"
    },
    {
        "website": "https://www.prakerja.go.id/"
    },
    {
        "website": "https://jdih.batan.go.id/"
    },
    {
        "website": "https://bkd.magetan.go.id/"
    },
    {
        "website": "https://www.brin.go.id/"
    },
    {
        "website": "https://www.bmkg.go.id/"
    },
    {
        "website": "https://covid19.metrokota.go.id/"
    },
    {
        "website": "https://www.bkpm.go.id/"
    },
    {
        "website": "https://disdukcapil.bekasikab.go.id/"
    },
    {
        "website": "https://bkddki.jakarta.go.id/"
    },
    {
        "website": "https://www.kemenpppa.go.id/"
    },
    {
        "website": "https://www.bkkbn.go.id/"
    },
    {
        "website": "https://bkd.blorakab.go.id/"
    },
    {
        "website": "https://lawancorona.batam.go.id/"
    },
    {
        "website": "https://www.kemendag.go.id/"
    },
    {
        "website": "https://www.pu.go.id/"
    },
    {
        "website": "https://www.malukubaratdayakab.go.id/"
    },
    {
        "website": "https://casn.kemkes.go.id/"
    },
    {
        "website": "https://www.anri.go.id/"
    },
    {
        "website": "http://bkd.jatimprov.go.id/"
    },
    {
        "website": "http://rsudalihsan.jabarprov.go.id/"
    },
    {
        "website": "http://cpns.pertanian.go.id/"
    },
    {
        "website": "https://kebudayaan.kemdikbud.go.id/"
    },
    {
        "website": "https://dinkopukm.grobogan.go.id/"
    },
    {
        "website": "https://cpns.kemdikbud.go.id/"
    },
    {
        "website": "https://labkesda.jakarta.go.id/"
    },
    {
        "website": "http://dinkes.sidoarjokab.go.id/"
    },
    {
        "website": "https://ppdb.sulselprov.go.id/"
    },
    {
        "website": "https://rpla.kemdikbud.go.id/"
    },
    {
        "website": "http://efaktur.pajak.go.id/"
    },
    {
        "website": "https://cpns.pu.go.id/"
    },
    {
        "website": "https://rekrutmen.kejaksaan.go.id/"
    },
    {
        "website": "https://www.inhilkab.go.id/"
    },
    {
        "website": "https://sinkarkes.kemkes.go.id/"
    },
    {
        "website": "https://bos.kemdikbud.go.id/"
    },
    {
        "website": "https://epresensi.kkp.go.id/"
    },
    {
        "website": "https://rekrutmen.kemenperin.go.id/"
    },
    {
        "website": "https://skp.sumutprov.go.id/"
    },
    {
        "website": "https://oss.go.id/"
    },
    {
        "website": "https://semarangkota.go.id/"
    },
    {
        "website": "https://kemenperin.go.id/"
    },
    {
        "website": "https://kemensos.go.id/"
    },
    {
        "website": "https://sumedangkab.go.id/"
    },
    {
        "website": "https://bnpb.go.id/"
    },
    {
        "website": "https://ereg.pajak.go.id/"
    },
    {
        "website": "https://peraturan.go.id/"
    },
    {
        "website": "https://ppdb.bandungkab.go.id/"
    },
    {
        "website": "https://sukabumikab.go.id/"
    },
    {
        "website": "http://pom.go.id/"
    },
    {
        "website": "https://lasik.tangerangselatankota.go.id/"
    },
    {
        "website": "https://gresikkab.go.id/"
    },
    {
        "website": "https://situbondokab.go.id/"
    },
    {
        "website": "https://www.kendalkab.go.id/"
    },
    {
        "website": "https://www.semarangkab.go.id/"
    },
    {
        "website": "https://temanggungkab.go.id/"
    },
    {
        "website": "https://kuduskab.go.id/"
    },
    {
        "website": "https://www.batangkab.go.id/"
    },
    {
        "website": "https://www.batubarakab.go.id/"
    },
    {
        "website": "https://www.kebumenkab.go.id/"
    },
    {
        "website": "https://tangerangkab.go.id/"
    },
    {
        "website": "http://gunungkidulkab.go.id/"
    },
    {
        "website": "https://www.garutkab.go.id/"
    },
    {
        "website": "https://www.pekalongankab.go.id/"
    },
    {
        "website": "https://badungkab.go.id/"
    },
    {
        "website": "https://jenepontokab.go.id/"
    },
    {
        "website": "https://wonogirikab.go.id/"
    },
    {
        "website": "https://www.magelangkab.go.id/"
    },
    {
        "website": "https://bojonegorokab.go.id/"
    },
    {
        "website": "https://www.banglikab.go.id/"
    },
    {
        "website": "https://takalarkab.go.id/"
    },
    {
        "website": "https://bantulkab.go.id/"
    },
    {
        "website": "https://www.tabanankab.go.id/"
    },
    {
        "website": "https://www.bandungkab.go.id/"
    },
    {
        "website": "http://www.slemankab.go.id/"
    },
    {
        "website": "https://bulelengkab.go.id/"
    },
    {
        "website": "https://niasutarakab.go.id/"
    },
    {
        "website": "https://www.karawangkab.go.id/"
    },
    {
        "website": "https://mojokertokab.go.id/"
    },
    {
        "website": "https://www.tasikmalayakab.go.id/"
    },
    {
        "website": "https://www.banyuwangikab.go.id/"
    },
    {
        "website": "https://www.sidoarjokab.go.id/"
    },
    {
        "website": "https://www.muaraenimkab.go.id/"
    },
    {
        "website": "https://pacitankab.go.id/"
    },
    {
        "website": "https://www.banjarnegarakab.go.id/"
    },
    {
        "website": "https://bkppd.pasuruankab.go.id/"
    },
    {
        "website": "https://dairikab.go.id/"
    },
    {
        "website": "https://klatenkab.go.id/"
    },
    {
        "website": "https://kutaibaratkab.go.id/"
    },
    {
        "website": "https://www.kuningankab.go.id/"
    },
    {
        "website": "http://mamujukab.go.id/"
    },
    {
        "website": "https://bengkaliskab.go.id/"
    },
    {
        "website": "https://www.malangkab.go.id/"
    },
    {
        "website": "https://selumakab.go.id/"
    },
    {
        "website": "https://belitung.go.id/"
    },
    {
        "website": "http://www.karokab.go.id/"
    },
    {
        "website": "https://jembranakab.go.id/"
    },
    {
        "website": "http://www.simalungunkab.go.id/"
    },
    {
        "website": "https://humbanghasundutankab.go.id/"
    },
    {
        "website": "https://bkd.tegalkab.go.id/"
    },
    {
        "website": "https://lumajangkab.go.id/"
    },
    {
        "website": "https://www.gianyarkab.go.id/"
    },
    {
        "website": "http://www.acehjayakab.go.id/"
    },
    {
        "website": "https://www.lampungbaratkab.go.id/"
    },
    {
        "website": "https://www.pasamankab.go.id/"
    },
    {
        "website": "http://www.acehbesarkab.go.id/"
    },
    {
        "website": "https://www.purbalinggakab.go.id/"
    },
    {
        "website": "https://www.pakpakbharatkab.go.id/"
    },
    {
        "website": "https://www.sragenkab.go.id/"
    },
    {
        "website": "https://cilacapkab.go.id/"
    },
    {
        "website": "https://serangkab.go.id/"
    },
    {
        "website": "http://www.bangkalankab.go.id/"
    },
    {
        "website": "http://www.musirawaskab.go.id/"
    },
    {
        "website": "http://bkpsdm.acehtengahkab.go.id/"
    },
    {
        "website": "http://bkd.jombangkab.go.id/"
    },
    {
        "website": "https://kedirikab.go.id/"
    },
    {
        "website": "http://tulangbawangkab.go.id/"
    },
    {
        "website": "https://banyuasinkab.go.id/"
    },
    {
        "website": "https://www.benermeriahkab.go.id/"
    },
    {
        "website": "http://bkpsdm.pringsewukab.go.id/"
    },
    {
        "website": "https://www.sarmikab.go.id/"
    },
    {
        "website": "https://lamongankab.go.id/"
    },
    {
        "website": "http://gowakab.go.id/"
    },
    {
        "website": "https://bkpp.lomboktengahkab.go.id/"
    },
    {
        "website": "https://balangankab.go.id/"
    },
    {
        "website": "https://www.gresikkab.go.id/"
    },
    {
        "website": "https://www.grobogan.go.id/"
    },
    {
        "website": "https://www.blitarkab.go.id/"
    },
    {
        "website": "https://bengkulutengahkab.go.id/"
    },
    {
        "website": "https://samosirkab.go.id/"
    },
    {
        "website": "https://luwuutarakab.go.id/"
    },
    {
        "website": "https://bangkaselatankab.go.id/"
    },
    {
        "website": "https://bkpsdm.majalengkakab.go.id/"
    },
    {
        "website": "http://sidrapkab.go.id/"
    },
    {
        "website": "https://bulukumbakab.go.id/"
    },
    {
        "website": "http://boyolali.go.id/"
    },
    {
        "website": "https://tanjabtimkab.go.id/"
    },
    {
        "website": "https://www.oganilirkab.go.id/"
    },
    {
        "website": "https://klungkungkab.go.id/"
    },
    {
        "website": "http://bkd.probolinggokab.go.id/"
    },
    {
        "website": "https://madina.go.id/"
    },
    {
        "website": "https://sinjaikab.go.id/"
    },
    {
        "website": "https://ekin.ngawikab.go.id/"
    },
    {
        "website": "http://bkpsdm.pamekasankab.go.id/"
    },
    {
        "website": "https://kotabogor.go.id/"
    },
    {
        "website": "https://www.bekasikota.go.id/"
    },
    {
        "website": "https://www.kotaprabumulih.go.id/"
    },
    {
        "website": "https://www.jambikota.go.id/"
    },
    {
        "website": "https://www.mojokertokota.go.id/"
    },
    {
        "website": "https://www.pariamankota.go.id/"
    },
    {
        "website": "https://www.denpasarkota.go.id/"
    },
    {
        "website": "https://www.tangerangkota.go.id/"
    },
    {
        "website": "https://www.surabaya.go.id/"
    },
    {
        "website": "https://sukabumikota.go.id/"
    },
    {
        "website": "https://pekalongankota.go.id/"
    },
    {
        "website": "https://www.kedirikota.go.id/"
    },
    {
        "website": "https://www.gorontalokota.go.id/"
    },
    {
        "website": "https://palopokota.go.id/"
    },
    {
        "website": "https://pematangsiantar.go.id/"
    },
    {
        "website": "https://madiunkota.go.id/"
    },
    {
        "website": "https://bandung.go.id/"
    },
    {
        "website": "https://www.sibolgakota.go.id/"
    },
    {
        "website": "http://www.bukittinggikota.go.id/"
    },
    {
        "website": "http://sikeda.bukittinggikota.go.id/"
    },
    {
        "website": "https://malangkota.go.id/"
    },
    {
        "website": "https://www.depok.go.id/"
    },
    {
        "website": "https://www.dumaikota.go.id/"
    },
    {
        "website": "https://banjarkota.go.id/"
    },
    {
        "website": "https://www.pekanbaru.go.id/"
    },
    {
        "website": "https://www.pontianakkota.go.id/"
    },
    {
        "website": "https://jogjakota.go.id/"
    },
    {
        "website": "https://www.langsakota.go.id/"
    },
    {
        "website": "https://jdih.serangkota.go.id/"
    },
    {
        "website": "https://pasuruankota.go.id/"
    },
    {
        "website": "https://gunungsitolikota.go.id/"
    },
    {
        "website": "https://bandarlampungkota.go.id/"
    },
    {
        "website": "http://www.sabangkota.go.id/"
    },
    {
        "website": "https://www.kendarikota.go.id/"
    },
    {
        "website": "https://jakarta.go.id/"
    },
    {
        "website": "http://bkppd.samarindakota.go.id/"
    },
    {
        "website": "http://palembang.go.id/"
    },
    {
        "website": "https://cimahikota.go.id/"
    },
    {
        "website": "https://bkpsdmd.pangkalpinangkota.go.id/"
    },
    {
        "website": "https://tomohon.go.id/"
    },
    {
        "website": "https://portal.tasikmalayakota.go.id/"
    },
    {
        "website": "https://www.cirebonkota.go.id/"
    },
    {
        "website": "https://blitarkota.go.id/"
    },
    {
        "website": "https://www.tangerangselatankota.go.id/"
    },
    {
        "website": "https://bkpsdm.lubuklinggaukota.go.id/"
    },
    {
        "website": "https://bkpsdm.limapuluhkotakab.go.id/"
    },
    {
        "website": "https://www.batukota.go.id/"
    },
    {
        "website": "https://ambon.go.id/"
    },
    {
        "website": "https://portal.baubaukota.go.id/"
    },
    {
        "website": "https://www.tebingtinggikota.go.id/"
    },
    {
        "website": "http://bkpp.magelangkota.go.id/"
    },
    {
        "website": "https://banjarmasinkota.go.id/"
    },
    {
        "website": "https://www.padang.go.id/"
    },
    {
        "website": "https://www.lhokseumawekota.go.id/"
    },
    {
        "website": "https://bengkulukota.go.id/"
    },
    {
        "website": "https://www.tanjungpinangkota.go.id/"
    },
    {
        "website": "https://www.tegalkota.go.id/"
    },
    {
        "website": "https://bkd.pemkomedan.go.id/"
    },
    {
        "website": "https://kepo.solokkota.go.id/"
    },
    {
        "website": "https://probolinggokota.go.id/"
    },
    {
        "website": "https://bkpp.banjarbarukota.go.id/"
    },
    {
        "website": "https://payakumbuhkota.go.id/"
    },
    {
        "website": "https://salatiga.go.id/"
    },
    {
        "website": "http://www.lpse.jayapurakota.go.id/"
    },
    {
        "website": "https://www.singkawangkota.go.id/"
    },
    {
        "website": "https://www.bontangkota.go.id/"
    },
    {
        "website": "http://subulussalamkota.go.id/"
    },
    {
        "website": "https://pareparekota.go.id/"
    },
    {
        "website": "https://bantenprov.go.id/"
    },
    {
        "website": "https://bimakota.go.id/"
    },
    {
        "website": "http://bkd.manadokota.go.id/"
    },
    {
        "website": "https://bkpsdm.bandaacehkota.go.id/"
    },
    {
        "website": "https://surakarta.go.id/"
    },
    {
        "website": "https://kupangkota.go.id/"
    },
    {
        "website": "https://sorongkota.go.id/"
    },
    {
        "website": "https://www.batam.go.id/"
    },
    {
        "website": "https://ternatekota.go.id/"
    },
    {
        "website": "http://www.cilegon.go.id/"
    },
    {
        "website": "https://sipd.kemendagri.go.id/"
    },
    {
        "website": "http://www.pagaralamkota.go.id/"
    },
    {
        "website": "https://sungaipenuhkota.go.id/"
    },
    {
        "website": "http://tarakankota.go.id/"
    },
    {
        "website": "http://bkpsdm.malangkab.go.id/"
    },
    {
        "website": "https://kaltimprov.go.id/"
    },
    {
        "website": "http://www.balikpapan.go.id/"
    },
    {
        "website": "https://tanjungbalaikota.go.id/"
    },
    {
        "website": "https://bkpsdm.sawahluntokota.go.id/"
    },
    {
        "website": "https://bkpsdm.gayolueskab.go.id/"
    },
    {
        "website": "https://www.bitungkota.go.id/"
    },
    {
        "website": "https://sma.sigum.binjaikota.go.id/"
    },
    {
        "website": "http://kotamobagukota.go.id/"
    },
    {
        "website": "https://www.jatimprov.go.id/"
    },
    {
        "website": "https://www.sumbarprov.go.id/"
    },
    {
        "website": "https://kalbarprov.go.id/"
    },
    {
        "website": "https://malukuprov.go.id/"
    },
    {
        "website": "https://jambiprov.go.id/"
    },
    {
        "website": "https://www.lampungprov.go.id/"
    },
    {
        "website": "https://gorontaloprov.go.id/"
    },
    {
        "website": "https://www.sumutprov.go.id/"
    },
    {
        "website": "https://www.acehprov.go.id/"
    },
    {
        "website": "http://www.sumselprov.go.id/"
    },
    {
        "website": "https://www.kalteng.go.id/"
    },
    {
        "website": "https://bengkuluprov.go.id/"
    },
    {
        "website": "https://sulselprov.go.id/"
    },
    {
        "website": "https://www.kaltaraprov.go.id/"
    },
    {
        "website": "https://www.baliprov.go.id/"
    },
    {
        "website": "https://www.sulutprov.go.id/"
    },
    {
        "website": "https://www.pdkjateng.go.id/"
    },
    {
        "website": "https://www.bkd.nttprov.go.id/"
    },
    {
        "website": "https://www.papua.go.id/"
    },
    {
        "website": "https://jogjaprov.go.id/"
    },
    {
        "website": "https://www.sultraprov.go.id/"
    },
    {
        "website": "https://www.malutprov.go.id/"
    },
    {
        "website": "https://kalselprov.go.id/"
    },
    {
        "website": "https://www.ntbprov.go.id/"
    },
    {
        "website": "http://www.sulbarprov.go.id/"
    },
    {
        "website": "https://jateng.bps.go.id/"
    },
    {
        "website": "https://bkpsdm.kepriprov.go.id/"
    },
    {
        "website": "https://papuabaratprov.go.id/"
    },
    {
        "website": "https://bkd.riau.go.id/"
    },
    {
        "website": "https://babelprov.go.id/"
    },
    {
        "website": "https://sultengprov.go.id/"
    },
    {
        "website": "https://www.bkn.go.id/"
    },
    {
        "website": "https://www.dinkesjatengprov.go.id/"
    },
    {
        "website": "https://siharka.menpan.go.id/"
    },
    {
        "website": "https://info.dipendajatim.go.id/"
    },
    {
        "website": "https://covid19.go.id/"
    },
    {
        "website": "https://ekinerja.banjarnegarakab.go.id/"
    },
    {
        "website": "https://www.atrbpn.go.id/"
    },
    {
        "website": "https://pusatprestasinasional.kemdikbud.go.id/"
    },
    {
        "website": "https://disdukcapil.pontianakkota.go.id/"
    },
    {
        "website": "http://www.lkpp.go.id/"
    },
    {
        "website": "https://probolinggokab.go.id/"
    },
    {
        "website": "https://domain.go.id/"
    },
    {
        "website": "https://dinkesp2kb.probolinggokota.go.id/"
    },
    {
        "website": "https://sippadu.bojonegorokab.go.id/"
    },
    {
        "website": "https://izin.purworejokab.go.id/"
    },
    {
        "website": "https://dpmptsp.bogorkab.go.id/"
    },
    {
        "website": "https://prodibaru.kopertis7.go.id/"
    },
    {
        "website": "https://putusan.mahkamahagung.go.id/"
    },
    {
        "website": "https://www.mahkamahagung.go.id/"
    },
    {
        "website": "https://www.dgip.go.id/"
    },
    {
        "website": "https://www.kominfo.go.id/"
    },
    {
        "website": "https://www.pajak.go.id/"
    },
    {
        "website": "https://vokasi.kemdikbud.go.id/"
    },
    {
        "website": "http://hubud.dephub.go.id/"
    },
    {
        "website": "https://www.kemhan.go.id/"
    },
    {
        "website": "https://djpb.kemenkeu.go.id/"
    },
    {
        "website": "https://www.beacukai.go.id/"
    },
    {
        "website": "https://sda.pu.go.id/"
    },
    {
        "website": "http://ditjenppi.menlhk.go.id/"
    },
    {
        "website": "http://www.pn-serang.go.id/"
    },
    {
        "website": "https://ditjenbun.pertanian.go.id/"
    },
    {
        "website": "https://ditjennak.pertanian.go.id/"
    },
    {
        "website": "https://bangda.kemendagri.go.id/"
    },
    {
        "website": "http://pt-banten.go.id/"
    },
    {
        "website": "https://madrasah.kemenag.go.id/"
    },
    {
        "website": "https://bimaskristen.kemenag.go.id/"
    },
    {
        "website": "https://kesga.kemkes.go.id/"
    },
    {
        "website": "http://ditpolkom.bappenas.go.id/"
    },
    {
        "website": "https://www.bin.go.id/"
    },
    {
        "website": "http://pn-sleman.go.id/"
    },
    {
        "website": "http://pn-unaaha.go.id/"
    },
    {
        "website": "https://www.pusair-pu.go.id/"
    },
    {
        "website": "https://ebtke.esdm.go.id/"
    },
    {
        "website": "https://kkp.go.id/"
    },
    {
        "website": "https://www.pa-kediri.go.id/"
    },
    {
        "website": "http://www.ojk.go.id/"
    },
    {
        "website": "https://kemnaker.go.id/"
    },
    {
        "website": "http://ditjenpp.kemenkumham.go.id/"
    },
    {
        "website": "http://pn-labuanbajo.go.id/"
    },
    {
        "website": "https://lpse.sukamarakab.go.id/"
    },
    {
        "website": "http://www.pn-fakfak.go.id/"
    },
    {
        "website": "http://pn-pangkalanbun.go.id/"
    },
    {
        "website": "https://www.bps.go.id/"
    },
    {
        "website": "http://www.pn-pandeglang.go.id/"
    },
    {
        "website": "https://www.polri.go.id/"
    },
    {
        "website": "https://pn-palu.go.id/"
    },
    {
        "website": "https://www.pa-muarabulian.go.id/"
    },
    {
        "website": "https://bkpp-kk.kotamobagukota.go.id/"
    },
    {
        "website": "https://siks.kemensos.go.id/"
    },
    {
        "website": "http://ditjendaglu.kemendag.go.id/"
    },
    {
        "website": "https://sertifikasicdob.pom.go.id/"
    },
    {
        "website": "http://www.pn-rangkasbitung.go.id/"
    },
    {
        "website": "https://www.perpusnas.go.id/"
    },
    {
        "website": "http://www.pn-parigi.go.id/"
    },
    {
        "website": "https://bakamla.go.id/"
    },
    {
        "website": "https://www.kejaksaan.go.id/"
    },
    {
        "website": "http://pn-sorong.go.id/"
    },
    {
        "website": "http://pa-jepara.go.id/"
    },
    {
        "website": "https://www.pta-bandarlampung.go.id/"
    },
    {
        "website": "https://www.pn-tolitoli.go.id/"
    },
    {
        "website": "https://www.pta-medan.go.id/"
    },
    {
        "website": "http://pn-merauke.go.id/"
    },
    {
        "website": "https://www.pa-cilegon.go.id/"
    },
    {
        "website": "https://pn-banjarnegara.go.id/"
    },
    {
        "website": "https://www.pn-mataram.go.id/"
    },
    {
        "website": "https://www.bandung.basarnas.go.id/"
    },
    {
        "website": "https://jdih.setkab.go.id/"
    },
    {
        "website": "https://www.menlhk.go.id/"
    },
    {
        "website": "http://ropeg.menlhk.go.id/"
    },
    {
        "website": "https://kemenparekraf.go.id/"
    },
    {
        "website": "https://www.kemendagri.go.id/"
    },
    {
        "website": "https://www.ekon.go.id/"
    },
    {
        "website": "https://www.kemenkeu.go.id/"
    },
    {
        "website": "https://www.kemdikbud.go.id/"
    },
    {
        "website": "https://bumn.go.id/"
    },
    {
        "website": "https://www.kemenkumham.go.id/"
    },
    {
        "website": "https://www.bappenas.go.id/"
    },
    {
        "website": "https://www.pertanian.go.id/"
    },
    {
        "website": "https://www.kemendesa.go.id/"
    },
    {
        "website": "https://pelaut.dephub.go.id/"
    },
    {
        "website": "https://kemenkopukm.go.id/"
    },
    {
        "website": "https://cekbpom.pom.go.id/"
    },
    {
        "website": "https://esdm.jatengprov.go.id/"
    },
    {
        "website": "https://www.kemenkopmk.go.id/"
    },
    {
        "website": "https://www.kemkes.go.id/"
    },
    {
        "website": "https://bkpsdm.acehsingkilkab.go.id/"
    },
    {
        "website": "https://setkab.go.id/"
    },
    {
        "website": "https://polkam.go.id/"
    },
    {
        "website": "https://jdih.esdm.go.id/"
    },
    {
        "website": "https://maritim.go.id/"
    },
    {
        "website": "https://wajiblapor.kemnaker.go.id/"
    },
    {
        "website": "https://sinta.ristekbrin.go.id/"
    },
    {
        "website": "https://brg.go.id/"
    },
    {
        "website": "https://dinkes.mubakab.go.id/"
    },
    {
        "website": "https://www.pt-medan.go.id/"
    },
    {
        "website": "http://jdih.sangihekab.go.id/"
    },
    {
        "website": "http://lpse.sulbarprov.go.id/"
    },
    {
        "website": "http://jdih.kkp.go.id/"
    },
    {
        "website": "http://pa-tasikmalayakota.go.id/"
    },
    {
        "website": "https://sumbarprov.go.id/"
    },
    {
        "website": "https://sicantikui.layanan.go.id/"
    },
    {
        "website": "https://www.jogjakota.go.id/"
    },
    {
        "website": "https://peduli.ojk.go.id/"
    },
    {
        "website": "https://silacak.kemkes.go.id/"
    },
    {
        "website": "https://siprestasi.nganjukkab.go.id/"
    },
    {
        "website": "https://sirup.lkpp.go.id/"
    },
    {
        "website": "https://siplah.kemdikbud.go.id/"
    },
    {
        "website": "https://sirusa.bps.go.id/"
    },
    {
        "website": "https://sieka.kemenag.go.id/"
    },
    {
        "website": "https://www.skkmigas.go.id/"
    },
    {
        "website": "https://layanan.kominfo.go.id/"
    },
    {
        "website": "https://sipencatar.dephub.go.id/"
    },
    {
        "website": "http://sihandal.kkp.go.id/"
    },
    {
        "website": "https://ppid.cilacapkab.go.id/"
    },
    {
        "website": "http://www.tpp.jayapurakota.go.id/"
    },
    {
        "website": "https://dispendik.situbondokab.go.id/"
    },
    {
        "website": "http://www.simeuluekab.go.id/"
    },
    {
        "website": "http://halal.go.id/"
    },
    {
        "website": "https://www.kpu.go.id/"
    },
    {
        "website": "https://si.disperakim.jatengprov.go.id/"
    },
    {
        "website": "https://bkpsdm.bogorkab.go.id/"
    },
    {
        "website": "https://bkpsdm.mataramkota.go.id/"
    },
    {
        "website": "https://simantu.pu.go.id/"
    },
    {
        "website": "https://www.blorakab.go.id/"
    },
    {
        "website": "https://dukcapil.trenggalekkab.go.id/"
    },
    {
        "website": "https://elearning.disdik.kalteng.go.id/"
    },
    {
        "website": "https://simpeg.kemenkumham.go.id/"
    },
    {
        "website": "https://siujang.esdm.go.id/"
    },
    {
        "website": "https://dinkes.batangkab.go.id/"
    },
    {
        "website": "https://bkpsdm.pidiejayakab.go.id/"
    },
    {
        "website": "https://bpsdm.acehprov.go.id/"
    },
    {
        "website": "https://niaskab.go.id/"
    },
    {
        "website": "https://perizinanonline.depok.go.id/"
    },
    {
        "website": "https://poedak.gresikkab.go.id/"
    },
    {
        "website": "https://cianjurkab.go.id/"
    },
    {
        "website": "https://sibijak.bpkp.go.id/"
    },
    {
        "website": "https://dukcapil.kuburayakab.go.id/"
    },
    {
        "website": "https://siakkab.go.id/"
    },
    {
        "website": "https://www.lapor.go.id/"
    },
    {
        "website": "https://www.bpk.go.id/"
    },
    {
        "website": "https://www.bi.go.id/"
    },
    {
        "website": "https://bappeda.sumselprov.go.id/"
    },
    {
        "website": "https://lapakasik.bpjsketenagakerjaan.go.id/"
    },
    {
        "website": "https://diskominfo.pontianakkota.go.id/"
    },
    {
        "website": "https://sipd.go.id/"
    },
    {
        "website": "https://ppid.ntbprov.go.id/"
    },
    {
        "website": "https://upt-perpusbunghatta.perpusnas.go.id/"
    },
    {
        "website": "https://www.postel.go.id/"
    },
    {
        "website": "http://pskl.menlhk.go.id/"
    },
    {
        "website": "https://bp2mi.go.id/"
    },
    {
        "website": "https://upt-pptp.bangkaselatankab.go.id/"
    },
    {
        "website": "https://surabaya.disnakertrans.jatimprov.go.id/"
    },
    {
        "website": "https://jabar.kemenkumham.go.id/"
    },
    {
        "website": "http://dinkes.karanganyarkab.go.id/"
    },
    {
        "website": "http://bppsdmp.pertanian.go.id/"
    },
    {
        "website": "https://p3tki-jatim.go.id/"
    },
    {
        "website": "https://pelayanan.jakarta.go.id/"
    },
    {
        "website": "http://dispenda.kepriprov.go.id/"
    },
    {
        "website": "https://ppdb.makassar.go.id/"
    },
    {
        "website": "https://dinkes.banyuasinkab.go.id/"
    },
    {
        "website": "https://bappenda.bogorkab.go.id/"
    },
    {
        "website": "https://jss.jogjakota.go.id/"
    },
    {
        "website": "https://dispendik.blitarkab.go.id/"
    },
    {
        "website": "https://badanpendapatan.riau.go.id/"
    },
    {
        "website": "http://bpi.lipi.go.id/"
    },
    {
        "website": "http://sdp.ditjenpas.go.id/"
    },
    {
        "website": "https://sumberdayaair.malangkab.go.id/"
    },
    {
        "website": "http://lpse.bandung.go.id/"
    },
    {
        "website": "https://bapenda.deliserdangkab.go.id/"
    },
    {
        "website": "https://www.kemenpora.go.id/"
    },
    {
        "website": "https://rsuddrsoedirman.kebumenkab.go.id/"
    },
    {
        "website": "https://dikes.badungkab.go.id/"
    },
    {
        "website": "http://skp2020.sidoarjokab.go.id/"
    },
    {
        "website": "https://diskopperindag.serangkab.go.id/"
    },
    {
        "website": "http://dinastph.sumutprov.go.id/"
    },
    {
        "website": "https://ppdb.pemkomedan.go.id/"
    },
    {
        "website": "http://ppk.bkipm.kkp.go.id/"
    },
    {
        "website": "https://dpu.kulonprogokab.go.id/"
    },
    {
        "website": "https://dkp.jatengprov.go.id/"
    },
    {
        "website": "https://gunungkidulkab.go.id/"
    },
    {
        "website": "https://sdm.data.kemdikbud.go.id/"
    },
    {
        "website": "http://sdm.pddikti.ristekdikti.go.id/"
    },
    {
        "website": "https://www.sdm.kemenkeu.go.id/"
    },
    {
        "website": "https://sdm.surabaya.go.id/"
    },
    {
        "website": "https://sdm.ekon.go.id/"
    },
    {
        "website": "http://esdm.pariamankota.go.id/"
    },
    {
        "website": "https://bkpsdm.subang.go.id/"
    },
    {
        "website": "https://ppsdmaparatur.esdm.go.id/"
    },
    {
        "website": "https://sidia.kemenperin.go.id/"
    },
    {
        "website": "https://bkpsdm.naganrayakab.go.id/"
    },
    {
        "website": "https://bkpsdm.situbondokab.go.id/"
    },
    {
        "website": "https://www.bkpsdm.majalengkakab.go.id/"
    },
    {
        "website": "https://ppsdm.atrbpn.go.id/"
    },
    {
        "website": "http://bkpsdm.acehbaratdayakab.go.id/"
    },
    {
        "website": "https://bpsdm.pu.go.id/"
    },
    {
        "website": "https://kepegawaian.paserkab.go.id/"
    },
    {
        "website": "https://www.bpsdm.jakarta.go.id/"
    },
    {
        "website": "https://bkpsdm.klungkungkab.go.id/"
    },
    {
        "website": "https://bkpsdm.acehselatankab.go.id/"
    },
    {
        "website": "https://bkpsdm.dumaikota.go.id/"
    },
    {
        "website": "https://bkpsdm.kuningankab.go.id/"
    },
    {
        "website": "https://ppsdma.bpsdm.dephub.go.id/"
    },
    {
        "website": "https://bpsdm.sumbarprov.go.id/"
    },
    {
        "website": "http://www.ropeg.kkp.go.id/"
    },
    {
        "website": "https://sdmpkh.kemensos.go.id/"
    },
    {
        "website": "https://penerimaan.polri.go.id/"
    },
    {
        "website": "https://pusdiklat.perpusnas.go.id/"
    },
    {
        "website": "https://bkpsdm.dharmasrayakab.go.id/"
    },
    {
        "website": "http://bkpsdm.padangpariamankab.go.id/"
    },
    {
        "website": "https://bkpsdm.baritoselatankab.go.id/"
    },
    {
        "website": "https://bkpsdm.kapuashulukab.go.id/"
    },
    {
        "website": "https://bkpsdm.batam.go.id/"
    },
    {
        "website": "http://bkpsdm.pidiekab.go.id/"
    },
    {
        "website": "https://bpsdmd.bantenprov.go.id/"
    },
    {
        "website": "https://bkpsdm.solselkab.go.id/"
    },
    {
        "website": "https://e-cpns.kemlu.go.id/"
    },
    {
        "website": "https://ppsdm.pom.go.id/"
    },
    {
        "website": "https://bkpsdm.badungkab.go.id/"
    },
    {
        "website": "https://bkpsdm.sampangkab.go.id/"
    },
    {
        "website": "https://bkpsdm.malangkota.go.id/"
    },
    {
        "website": "https://bkpsdm.bulelengkab.go.id/"
    },
    {
        "website": "https://bkpsdm.hulusungaiselatankab.go.id/"
    },
    {
        "website": "http://bkpsdm.sekadaukab.go.id/"
    },
    {
        "website": "https://bkpsdm.rohilkab.go.id/"
    },
    {
        "website": "https://balitbangsdm.kominfo.go.id/"
    },
    {
        "website": "https://bkpsdm.jembranakab.go.id/"
    },
    {
        "website": "https://bkpsdm.melawikab.go.id/"
    },
    {
        "website": "http://bpsdm.kemenkumham.go.id/"
    },
    {
        "website": "https://bpsdm.jatimprov.go.id/"
    },
    {
        "website": "https://bkpsdmad.sambas.go.id/"
    },
    {
        "website": "http://bkpsdm.pesawarankab.go.id/"
    },
    {
        "website": "http://sisdmk.kemkes.go.id/"
    },
    {
        "website": "https://bpsdm.riau.go.id/"
    },
    {
        "website": "https://baperlitbang.kendalkab.go.id/"
    },
    {
        "website": "https://bkpsdm.tangerangkota.go.id/"
    },
    {
        "website": "https://bkpsdm.luwuutarakab.go.id/"
    },
    {
        "website": "https://bpsdm.kalteng.go.id/"
    },
    {
        "website": "https://bkpsdm.serangkota.go.id/"
    },
    {
        "website": "https://bkpsdmd.makassar.go.id/"
    },
    {
        "website": "https://pusbangsdm.kemenparekraf.go.id/"
    },
    {
        "website": "http://bkpsdmd.morowalikab.go.id/"
    },
    {
        "website": "http://bkpsdm.acehbesarkab.go.id/"
    },
    {
        "website": "http://bkpsdm.tubankab.go.id/"
    },
    {
        "website": "https://bkpsdmd.babelprov.go.id/"
    },
    {
        "website": "https://bpsdm.lampungprov.go.id/"
    },
    {
        "website": "https://bkpsdm.bimakota.go.id/"
    },
    {
        "website": "http://bp2sdm.menlhk.go.id/"
    },
    {
        "website": "http://bkpsdm.sukabumikab.go.id/"
    },
    {
        "website": "https://bkpsdm.depok.go.id/"
    },
    {
        "website": "http://bpsdm.sumutprov.go.id/"
    },
    {
        "website": "https://bpsdm.kemendagri.go.id/"
    },
    {
        "website": "https://bpsdm.papua.go.id/"
    },
    {
        "website": "https://sdm.big.go.id/"
    },
    {
        "website": "https://simpeg.tasikmalayakab.go.id/"
    },
    {
        "website": "https://bkpsdm.pontianakkota.go.id/"
    },
    {
        "website": "https://lan.go.id/"
    },
    {
        "website": "http://bkpsdm.palembang.go.id/"
    },
    {
        "website": "https://ppsdm.lkpp.go.id/"
    },
    {
        "website": "https://bkd.jambikota.go.id/"
    },
    {
        "website": "https://www.kejari-bone.go.id/"
    },
    {
        "website": "https://sscasn.bkn.go.id/"
    },
    {
        "website": "https://bkd.sumbarprov.go.id/"
    },
    {
        "website": "http://www.bpkp.go.id/"
    },
    {
        "website": "https://bkppd.klatenkab.go.id/"
    },
    {
        "website": "https://bkd.sulutprov.go.id/"
    },
    {
        "website": "https://djponline.pajak.go.id/"
    },
    {
        "website": "http://ult.kemdikbud.go.id/"
    },
    {
        "website": "https://www.basarnas.go.id/"
    },
    {
        "website": "https://htel.atrbpn.go.id/"
    },
    {
        "website": "https://aksespembiayaan.kemenparekraf.go.id/"
    },
    {
        "website": "https://ditjenmiltun.mahkamahagung.go.id/"
    },
    {
        "website": "https://lelang.go.id/"
    },
    {
        "website": "https://bkpp.gorontalokota.go.id/"
    },
    {
        "website": "https://bkd.jepara.go.id/"
    },
    {
        "website": "https://www.big.go.id/"
    },
    {
        "website": "https://bkpsdm.acehbaratkab.go.id/"
    },
    {
        "website": "https://www.kkp.go.id/"
    },
    {
        "website": "https://bkpp.kendalkab.go.id/"
    },
    {
        "website": "https://bkppd.cianjurkab.go.id/"
    },
    {
        "website": "https://bkd.grobogan.go.id/"
    },
    {
        "website": "https://bkpp.slemankab.go.id/"
    },
    {
        "website": "https://bkpsdm.temanggungkab.go.id/"
    },
    {
        "website": "http://bkd.bengkuluprov.go.id/"
    },
    {
        "website": "https://bkad.bantulkab.go.id/"
    },
    {
        "website": "https://badiklat.kejaksaan.go.id/"
    },
    {
        "website": "https://bpjs-kesehatan.go.id/"
    },
    {
        "website": "https://bkpsdm.banyuasinkab.go.id/"
    },
    {
        "website": "https://bkdiklat.cirebonkota.go.id/"
    },
    {
        "website": "https://bkpsdm.lomboktimurkab.go.id/"
    },
    {
        "website": "https://bkpsdm.muaraenimkab.go.id/"
    },
    {
        "website": "https://tanahair.indonesia.go.id/"
    },
    {
        "website": "https://bkpsdm.acehtamiangkab.go.id/"
    },
    {
        "website": "https://bpkn.go.id/"
    },
    {
        "website": "https://e-resources.perpusnas.go.id/"
    },
    {
        "website": "https://www.instagram.com/"
    },
    {
        "website": "https://www.bsn.go.id/"
    },
    {
        "website": "https://www.bnpt.go.id/"
    },
    {
        "website": "https://jdihn.go.id/"
    },
    {
        "website": "https://den.go.id/"
    },
    {
        "website": "https://cpns.lipi.go.id/"
    },
    {
        "website": "http://mhn.bphn.go.id/"
    },
    {
        "website": "https://sirup-lat.lkpp.go.id/"
    },
    {
        "website": "https://www.wantiknas.go.id/"
    },
    {
        "website": "https://sisrute.kemkes.go.id/"
    },
    {
        "website": "http://www.tnp2k.go.id/"
    },
    {
        "website": "http://www.batan.go.id/"
    },
    {
        "website": "https://spbn.pusfatja.lapan.go.id/"
    },
    {
        "website": "https://baznas.go.id/"
    },
    {
        "website": "http://www.lemhannas.go.id/"
    },
    {
        "website": "https://www.esdm.go.id/"
    },
    {
        "website": "https://www.ojk.go.id/"
    },
    {
        "website": "https://kppip.go.id/"
    },
    {
        "website": "https://kek.go.id/"
    },
    {
        "website": "https://www.djsn.go.id/"
    },
    {
        "website": "http://www.dephub.go.id/"
    },
    {
        "website": "https://siinas.kemenperin.go.id/"
    },
    {
        "website": "https://bnsp.go.id/"
    },
    {
        "website": "https://www.bppt.go.id/"
    },
    {
        "website": "https://skkni.kemnaker.go.id/"
    },
    {
        "website": "https://pjnhk.go.id/"
    },
    {
        "website": "https://www.belitungtimurkab.go.id/"
    },
    {
        "website": "https://sampangkab.go.id/"
    },
    {
        "website": "https://jikn.go.id/"
    },
    {
        "website": "http://arjuna.ristekbrin.go.id/"
    },
    {
        "website": "https://www.komnasperempuan.go.id/"
    },
    {
        "website": "https://komisiinformasi.go.id/"
    },
    {
        "website": "https://iar-ikrap.postel.go.id/"
    },
    {
        "website": "https://bos.kemenag.go.id/"
    },
    {
        "website": "https://bansm.kemdikbud.go.id/"
    },
    {
        "website": "https://web-efaktur.pajak.go.id/"
    },
    {
        "website": "https://www.dprd-diy.go.id/"
    },
    {
        "website": "https://pa-lewoleba.go.id/"
    },
    {
        "website": "http://lpse.batangharikab.go.id/"
    },
    {
        "website": "https://yankes.kemkes.go.id/"
    },
    {
        "website": "https://tapera.go.id/"
    },
    {
        "website": "https://lpse.lomboktengahkab.go.id/"
    },
    {
        "website": "https://simonika2.kpu.go.id/"
    },
    {
        "website": "http://ppdb.bandung.go.id/"
    },
    {
        "website": "https://ntt.kemenkumham.go.id/"
    },
    {
        "website": "http://bkd.banyuwangikab.go.id/"
    },
    {
        "website": "https://survei.balitbangham.go.id/"
    },
    {
        "website": "https://anggaran.kemenkeu.go.id/"
    },
    {
        "website": "https://dpkd.sumbarprov.go.id/"
    },
    {
        "website": "https://sdgsdesa.kemendesa.go.id/"
    },
    {
        "website": "https://pn-lubukbasung.go.id/"
    },
    {
        "website": "http://nabirekab.go.id/"
    },
    {
        "website": "http://www.kemendagri.go.id/"
    },
    {
        "website": "https://kpu-tabanankab.go.id/"
    },
    {
        "website": "http://jdih.bpk.go.id/"
    },
    {
        "website": "https://kip.bandaacehkota.go.id/"
    },
    {
        "website": "http://lpse.gowakab.go.id/"
    },
    {
        "website": "http://pusbindiklatren.bappenas.go.id/"
    },
    {
        "website": "https://elhkpn.kpk.go.id/"
    },
    {
        "website": "http://mutasi.sdm.kemdikbud.go.id/"
    },
    {
        "website": "https://menpan.go.id/"
    },
    {
        "website": "https://casn.esdm.go.id/"
    },
    {
        "website": "https://simpeg.batam.go.id/"
    },
    {
        "website": "https://www.lpdp.kemenkeu.go.id/"
    },
    {
        "website": "https://corona.jakarta.go.id/"
    },
    {
        "website": "https://balitbangham.go.id/"
    },
    {
        "website": "https://basarnas.go.id/"
    },
    {
        "website": "https://sekadaukab.go.id/"
    },
    {
        "website": "https://lkpmonline.bkpm.go.id/"
    },
    {
        "website": "https://binjaikota.go.id/"
    },
    {
        "website": "https://lpsk.go.id/"
    },
    {
        "website": "https://www.insw.go.id/"
    },
    {
        "website": "https://pangkalpinangkota.go.id/"
    },
    {
        "website": "https://www.presidenri.go.id/"
    },
    {
        "website": "https://www.kpk.go.id/"
    },
    {
        "website": "https://www.mpr.go.id/"
    },
    {
        "website": "https://www.komisiyudisial.go.id/"
    },
    {
        "website": "https://www.bawaslu.go.id/"
    },
    {
        "website": "https://jdih.setneg.go.id/"
    },
    {
        "website": "https://cpns.perpusnas.go.id/"
    },
    {
        "website": "https://dkpp.go.id/"
    },
    {
        "website": "https://www.wapresri.go.id/"
    },
    {
        "website": "https://www.lapan.go.id/"
    },
    {
        "website": "https://bpip.go.id/"
    },
    {
        "website": "https://data.go.id/"
    },
    {
        "website": "https://kppu.go.id/"
    },
    {
        "website": "https://www.imigrasi.go.id/"
    },
    {
        "website": "https://www.pa-negara.go.id/"
    },
    {
        "website": "https://komisi-kejaksaan.go.id/"
    },
    {
        "website": "https://bidikmisi.belmawa.ristekdikti.go.id/"
    },
    {
        "website": "http://tvri.go.id/"
    },
    {
        "website": "http://vervalptk.data.kemdikbud.go.id/"
    },
    {
        "website": "https://padangpariamankab.go.id/"
    },
    {
        "website": "https://trenggalekkab.go.id/"
    },
    {
        "website": "https://ngawikab.go.id/"
    },
    {
        "website": "https://bappeda.jatengprov.go.id/"
    },
    {
        "website": "https://diskominfo.pangkepkab.go.id/"
    },
    {
        "website": "http://www.bbpk.go.id/"
    },
    {
        "website": "https://www.sumselprov.go.id/"
    },
    {
        "website": "http://www.djpk.kemenkeu.go.id/"
    },
    {
        "website": "https://dispendukcapil.kedirikota.go.id/"
    },
    {
        "website": "https://www.ppatk.go.id/"
    },
    {
        "website": "https://diskominfo.sumutprov.go.id/"
    },
    {
        "website": "https://e-monev.bappenas.go.id/"
    },
    {
        "website": "https://bkpp.rokanhulukab.go.id/"
    },
    {
        "website": "https://sso.bpjsketenagakerjaan.go.id/"
    },
    {
        "website": "https://visa-online.imigrasi.go.id/"
    },
    {
        "website": "http://bkd.cilacapkab.go.id/"
    },
    {
        "website": "https://corona.jogjaprov.go.id/"
    },
    {
        "website": "http://covid19.kedirikab.go.id/"
    },
    {
        "website": "http://bappeda.jabarprov.go.id/"
    },
    {
        "website": "https://pilkada2020.kpu.go.id/"
    },
    {
        "website": "https://bkpp.patikab.go.id/"
    },
    {
        "website": "https://covid19.pacitankab.go.id/"
    },
    {
        "website": "http://bkd.tanahbumbukab.go.id/"
    },
    {
        "website": "https://dindik.jatimprov.go.id/"
    },
    {
        "website": "https://bkpsdm.malangkab.go.id/"
    },
    {
        "website": "https://www.pn-jakartautara.go.id/"
    },
    {
        "website": "https://sambas.go.id/"
    },
    {
        "website": "https://mataumkm.riau.go.id/"
    },
    {
        "website": "https://www.pta-jambi.go.id/"
    },
    {
        "website": "https://pt-palangkaraya.go.id/"
    },
    {
        "website": "http://www.pa-bangkinang.go.id/"
    },
    {
        "website": "https://mail.go.id/"
    },
    {
        "website": "https://nisn.data.kemdikbud.go.id/"
    },
    {
        "website": "https://www.labuhanbatuselatankab.go.id/"
    },
    {
        "website": "https://diskominfo.tangerangkota.go.id/"
    },
    {
        "website": "https://www.pn-bitung.go.id/"
    },
    {
        "website": "https://www.simponi.kemenkeu.go.id/"
    },
    {
        "website": "https://www.pt-bengkulu.go.id/"
    },
    {
        "website": "http://www.pn-jakartaselatan.go.id/"
    },
    {
        "website": "http://kerjaku.indramayukab.go.id/"
    },
    {
        "website": "https://www.pn-bandung.go.id/"
    },
    {
        "website": "https://rogatori.kemlu.go.id/"
    },
    {
        "website": "http://pn-sanggau.go.id/"
    },
    {
        "website": "https://disdik.kalteng.go.id/"
    },
    {
        "website": "https://pn-balebandung.go.id/"
    },
    {
        "website": "https://www.pn-muarateweh.go.id/"
    },
    {
        "website": "https://pa-painan.go.id/"
    },
    {
        "website": "https://www.pa-malangkab.go.id/"
    },
    {
        "website": "https://pa-pariaman.go.id/"
    },
    {
        "website": "https://www.pa-dumai.go.id/"
    },
    {
        "website": "https://pt-gorontalo.go.id/"
    },
    {
        "website": "http://www.pn-polewali.go.id/"
    },
    {
        "website": "http://www.pn-sampit.go.id/"
    },
    {
        "website": "https://boyolalikab.bps.go.id/"
    },
    {
        "website": "https://pn-palangkaraya.go.id/"
    },
    {
        "website": "http://www.pa-muarasabak.go.id/"
    },
    {
        "website": "https://www.pn-kualakapuas.go.id/"
    },
    {
        "website": "https://www.pa-bekasi.go.id/"
    },
    {
        "website": "https://www.pn-negara.go.id/"
    },
    {
        "website": "https://www.pta-makassar.go.id/"
    },
    {
        "website": "http://www.pn-saumlaki.go.id/"
    },
    {
        "website": "http://pt-denpasar.go.id/"
    },
    {
        "website": "https://pa-demak.go.id/"
    },
    {
        "website": "http://pn-kotaagung.go.id/"
    },
    {
        "website": "https://www.pa-surabaya.go.id/"
    },
    {
        "website": "https://www.pta-ambon.go.id/"
    },
    {
        "website": "http://www.pa-krui.go.id/"
    },
    {
        "website": "https://kominfo.go.id/"
    },
    {
        "website": "https://mysapk.bkn.go.id/"
    },
    {
        "website": "https://regvaksin.acehprov.go.id/"
    },
    {
        "website": "https://sippa.ciptakarya.pu.go.id/"
    },
    {
        "website": "http://ppei.kemendag.go.id/"
    },
    {
        "website": "https://dp3a.semarangkota.go.id/"
    },
    {
        "website": "https://www.bkd.garutkab.go.id/"
    },
    {
        "website": "https://dashboard-sdgs.kemendesa.go.id/"
    },
    {
        "website": "http://bkpp.cilegon.go.id/"
    },
    {
        "website": "https://covid19.tangerangkota.go.id/"
    },
    {
        "website": "https://bkd.wonosobokab.go.id/"
    },
    {
        "website": "https://itjen.kemenkumham.go.id/"
    },
    {
        "website": "https://gistaru.atrbpn.go.id/"
    },
    {
        "website": "https://jambikota.go.id/"
    },
    {
        "website": "http://pusfatja.lapan.go.id/"
    },
    {
        "website": "https://disdukcapil.bantulkab.go.id/"
    },
    {
        "website": "https://sab.ahu.go.id/"
    },
    {
        "website": "http://desasendoyan.id/"
    },
    {
        "website": "https://desaseimeran-pangkalansusu.id/"
    },
    {
        "website": "http://download.garuda.ristekdikti.go.id/"
    },
    {
        "website": "https://banglikab.go.id/"
    },
    {
        "website": "http://cpns.polri.go.id/"
    },
    {
        "website": "http://bkpp.labuhanbatukab.go.id/"
    },
    {
        "website": "http://bkpsdm.tanggamus.go.id/"
    },
    {
        "website": "https://diskominfo.kaltaraprov.go.id/"
    },
    {
        "website": "https://sitara.tapera.go.id/"
    },
    {
        "website": "https://vaksinasi.tangerangkota.go.id/"
    },
    {
        "website": "https://espm.kemenkeu.go.id/"
    },
    {
        "website": "https://bkpsdm.bandungbaratkab.go.id/"
    },
    {
        "website": "https://www.bantenprov.go.id/"
    },
    {
        "website": "https://www.tapteng.go.id/"
    },
    {
        "website": "https://dcktrp.jakarta.go.id/"
    },
    {
        "website": "https://berita.bolmutkab.go.id/"
    },
    {
        "website": "https://inspektorat.bppt.go.id/"
    },
    {
        "website": "https://psp.pertanian.go.id/"
    },
    {
        "website": "http://lpse.kemkes.go.id/"
    },
    {
        "website": "https://lpse.sanggau.go.id/"
    },
    {
        "website": "https://sertifikasi.postel.go.id/"
    },
    {
        "website": "https://mitrakab.go.id/"
    },
    {
        "website": "http://lpse.blitarkab.go.id/"
    },
    {
        "website": "https://sbmptnp.kemenparekraf.go.id/"
    },
    {
        "website": "https://bkad.kulonprogokab.go.id/"
    },
    {
        "website": "https://portal.deliserdangkab.go.id/"
    },
    {
        "website": "https://bkpsdm.bintankab.go.id/"
    },
    {
        "website": "https://pu.go.id/"
    },
    {
        "website": "https://www.tanahdatar.go.id/"
    },
    {
        "website": "https://bkd.lampungprov.go.id/"
    },
    {
        "website": "https://sumbawakab.go.id/"
    },
    {
        "website": "https://bkd.baliprov.go.id/"
    },
    {
        "website": "https://dompukab.go.id/"
    },
    {
        "website": "http://www.ttukab.go.id/"
    },
    {
        "website": "https://bkpsdm.lahatkab.go.id/"
    },
    {
        "website": "https://bkpsdm.serangkab.go.id/"
    },
    {
        "website": "https://lpse.sumutprov.go.id/"
    },
    {
        "website": "http://ppid.magelangkota.go.id/"
    },
    {
        "website": "https://dashboard.prakerja.go.id/"
    },
    {
        "website": "https://account.kemnaker.go.id/"
    },
    {
        "website": "http://temanggungkab.go.id/"
    },
    {
        "website": "https://kjp.jakarta.go.id/"
    },
    {
        "website": "http://www.pentaru.kkp.go.id/"
    },
    {
        "website": "https://antrian.bkpm.go.id/"
    },
    {
        "website": "http://www.palembang.go.id/"
    },
    {
        "website": "https://www.serdangbedagaikab.go.id/"
    },
    {
        "website": "http://www.kki.go.id/"
    },
    {
        "website": "https://pn-malang.go.id/"
    },
    {
        "website": "https://pn-surabayakota.go.id/"
    },
    {
        "website": "https://site.pn-jambi.go.id/"
    },
    {
        "website": "https://www.pn-ngawi.go.id/"
    },
    {
        "website": "https://pn-jakartatimur.go.id/"
    },
    {
        "website": "https://www.pn-banyumas.go.id/"
    },
    {
        "website": "https://pn-semarangkota.go.id/"
    },
    {
        "website": "https://www.pn-mentok.go.id/"
    },
    {
        "website": "https://pn-kupang.go.id/"
    },
    {
        "website": "https://www.pn-subang.go.id/"
    },
    {
        "website": "https://www.pn-blitar.go.id/"
    },
    {
        "website": "https://www.pn-samarinda.go.id/"
    },
    {
        "website": "https://pn-bekasikota.go.id/"
    },
    {
        "website": "https://pn-pontianak.go.id/"
    },
    {
        "website": "https://www.pn-amlapura.go.id/"
    },
    {
        "website": "https://www.pn-curup.go.id/"
    },
    {
        "website": "https://pn-klaten.go.id/"
    },
    {
        "website": "https://pn-praya.go.id/"
    },
    {
        "website": "https://pn-batam.go.id/"
    },
    {
        "website": "https://www.pn-magelang.go.id/"
    },
    {
        "website": "https://pn-bandaaceh.go.id/"
    },
    {
        "website": "https://www.pn-bintuhan.go.id/"
    },
    {
        "website": "https://pn-kayuagung.go.id/"
    },
    {
        "website": "https://pn-seirampah.go.id/"
    },
    {
        "website": "https://www.pn-tais.go.id/"
    },
    {
        "website": "https://www.pn-banjarnegara.go.id/"
    },
    {
        "website": "https://pn-pati.go.id/"
    },
    {
        "website": "https://www.pn-blambanganumpu.go.id/"
    },
    {
        "website": "https://pn-tobelo.go.id/"
    },
    {
        "website": "https://www.pn-sampang.go.id/"
    },
    {
        "website": "https://pn-tarakan.go.id/"
    },
    {
        "website": "https://www.pn-bantul.go.id/"
    },
    {
        "website": "https://pn-karawang.go.id/"
    },
    {
        "website": "https://www.pn-kisaran.go.id/"
    },
    {
        "website": "https://pn-sawahlunto.go.id/"
    },
    {
        "website": "https://pn-soe.go.id/"
    },
    {
        "website": "https://www.pn-gorontalo.go.id/"
    },
    {
        "website": "https://www.pn-kuningan.go.id/"
    },
    {
        "website": "https://www.pn-demak.go.id/"
    },
    {
        "website": "https://pn-marisa.go.id/"
    },
    {
        "website": "https://www.pn-selong.go.id/"
    },
    {
        "website": "https://www.pn-gianyar.go.id/"
    },
    {
        "website": "https://pn-tasikmalaya.go.id/"
    },
    {
        "website": "https://pn-kualakurun.go.id/"
    },
    {
        "website": "https://www.pn-kabanjahe.go.id/"
    },
    {
        "website": "https://pn-ambon.go.id/"
    },
    {
        "website": "https://pn-depok.go.id/"
    },
    {
        "website": "https://www.pn-sumber.go.id/"
    },
    {
        "website": "https://www.pn-sintang.go.id/"
    },
    {
        "website": "https://www.pn-trenggalek.go.id/"
    },
    {
        "website": "https://www.pn-bengkulu.go.id/"
    },
    {
        "website": "https://pn-bondowoso.go.id/"
    },
    {
        "website": "https://pn-slawi.go.id/"
    },
    {
        "website": "https://www.pn-muarabungo.go.id/"
    },
    {
        "website": "https://pa-sidoarjo.go.id/"
    },
    {
        "website": "https://www.pa-jakartaselatan.go.id/"
    },
    {
        "website": "https://pa-makassar.go.id/"
    },
    {
        "website": "https://www.pa-bogor.go.id/"
    },
    {
        "website": "https://pa-kasongan.go.id/"
    },
    {
        "website": "https://pa-tenggarong.go.id/"
    },
    {
        "website": "https://www.pa-jakartabarat.go.id/"
    },
    {
        "website": "https://www.pa-situbondo.go.id/"
    },
    {
        "website": "https://pa-semarang.go.id/"
    },
    {
        "website": "https://www.pa-poso.go.id/"
    },
    {
        "website": "https://www.pa-solok.go.id/"
    },
    {
        "website": "https://www.pa-jakartatimur.go.id/"
    },
    {
        "website": "https://www.pa-kendari.go.id/"
    },
    {
        "website": "https://pa-padang.go.id/"
    },
    {
        "website": "https://www.pa-raha.go.id/"
    },
    {
        "website": "https://www.pa-metro.go.id/"
    },
    {
        "website": "https://www.pa-cibinong.go.id/"
    },
    {
        "website": "https://pa-sukamara.go.id/"
    },
    {
        "website": "https://pa-palangkaraya.go.id/"
    },
    {
        "website": "https://www.pa-sanggau.go.id/"
    },
    {
        "website": "https://pa-tais.go.id/"
    },
    {
        "website": "https://pa-pangkajene.go.id/"
    },
    {
        "website": "https://pa-tembilahan.go.id/"
    },
    {
        "website": "https://pa-bangko.go.id/"
    },
    {
        "website": "https://pa-muaratebo.go.id/"
    },
    {
        "website": "https://www.pa-cikarang.go.id/"
    },
    {
        "website": "https://pa-soreang.go.id/"
    },
    {
        "website": "https://www.pa-ambarawa.go.id/"
    },
    {
        "website": "https://www.pa-masohi.go.id/"
    },
    {
        "website": "https://www.pa-klaten.go.id/"
    },
    {
        "website": "https://www.pa-sukadana.go.id/"
    },
    {
        "website": "https://www.pa-padangpanjang.go.id/"
    },
    {
        "website": "https://pa-muarabungo.go.id/"
    },
    {
        "website": "https://pa-masamba.go.id/"
    },
    {
        "website": "https://www.pa-manna.go.id/"
    },
    {
        "website": "https://pa-sarolangun.go.id/"
    },
    {
        "website": "https://pa-bangil.go.id/"
    },
    {
        "website": "https://www.pa-pelaihari.go.id/"
    },
    {
        "website": "https://www.pa-boyolali.go.id/"
    },
    {
        "website": "https://www.pa-gresik.go.id/"
    },
    {
        "website": "https://www.pa-soasio.go.id/"
    },
    {
        "website": "https://www.pa-jombang.go.id/"
    },
    {
        "website": "https://www.pa-ambon.go.id/"
    },
    {
        "website": "https://www.pa-gedongtataan.go.id/"
    },
    {
        "website": "https://www.pa-mempawah.go.id/"
    },
    {
        "website": "https://www.pa-magetan.go.id/"
    },
    {
        "website": "https://www.pa-magelang.go.id/"
    },
    {
        "website": "https://pa-praya.go.id/"
    },
    {
        "website": "https://www.pa-maninjau.go.id/"
    },
    {
        "website": "https://web.pa-sumber.go.id/"
    },
    {
        "website": "https://www.pa-kudus.go.id/"
    },
    {
        "website": "https://pa-binjai.go.id/"
    },
    {
        "website": "https://www.pa-penajam.go.id/"
    },
    {
        "website": "https://pa-palopo.go.id/"
    },
    {
        "website": "https://www.pa-gianyar.go.id/"
    },
    {
        "website": "https://www.pa-tanjungkarang.go.id/"
    },
    {
        "website": "https://web.pa-majalengka.go.id/"
    },
    {
        "website": "https://site.pa-jeneponto.go.id/"
    },
    {
        "website": "https://www.pa-purworejo.go.id/"
    },
    {
        "website": "https://pa-karangasem.go.id/"
    },
    {
        "website": "https://www.pa-bantaeng.go.id/"
    },
    {
        "website": "https://www.pa-bojonegoro.go.id/"
    },
    {
        "website": "https://www.pa-jambi.go.id/"
    },
    {
        "website": "https://pa-balikpapan.go.id/"
    },
    {
        "website": "https://pa-kotabumi.go.id/"
    },
    {
        "website": "https://pa-manado.go.id/"
    },
    {
        "website": "https://www.pa-simalungun.go.id/"
    },
    {
        "website": "https://www.pa-kayuagung.go.id/"
    },
    {
        "website": "https://www.pa-wonosobo.go.id/"
    },
    {
        "website": "https://pa-jakartapusat.go.id/"
    },
    {
        "website": "https://www.pa-pandeglang.go.id/"
    },
    {
        "website": "https://www.pa-sendawar.go.id/"
    },
    {
        "website": "https://lpse.pu.go.id/"
    },
    {
        "website": "https://ulp.pu.go.id/"
    },
    {
        "website": "https://sigi.pu.go.id/"
    },
    {
        "website": "https://sipbj.pu.go.id/"
    },
    {
        "website": "https://ehrm.pu.go.id/"
    },
    {
        "website": "https://simbg.pu.go.id/"
    },
    {
        "website": "https://perumahan.pu.go.id/"
    },
    {
        "website": "https://pustaka.pu.go.id/"
    },
    {
        "website": "https://jdih.pu.go.id/"
    },
    {
        "website": "https://binakonstruksi.pu.go.id/"
    },
    {
        "website": "https://eppid.pu.go.id/"
    },
    {
        "website": "https://setjen.pu.go.id/"
    },
    {
        "website": "https://data.pu.go.id/"
    },
    {
        "website": "https://pengaduan.pu.go.id/"
    },
    {
        "website": "https://binamarga.pu.go.id/"
    },
    {
        "website": "https://sibaru.perumahan.pu.go.id/"
    },
    {
        "website": "https://pu.papua.go.id/"
    },
    {
        "website": "https://pu.jogjakota.go.id/"
    },
    {
        "website": "https://dpu.ntbprov.go.id/"
    },
    {
        "website": "https://dpu.semarangkota.go.id/"
    },
    {
        "website": "https://www.lpse.jabarprov.go.id/"
    },
    {
        "website": "https://simojang.big.go.id/"
    },
    {
        "website": "https://lpse.tangerangkota.go.id/"
    },
    {
        "website": "https://lpse.dephub.go.id/"
    },
    {
        "website": "https://lpse.jatengprov.go.id/"
    },
    {
        "website": "https://lpse.kalbarprov.go.id/"
    },
    {
        "website": "https://pengairan.acehprov.go.id/"
    },
    {
        "website": "https://dpupr.kendalkab.go.id/"
    },
    {
        "website": "https://dpupr.bantenprov.go.id/"
    },
    {
        "website": "https://spanint.kemenkeu.go.id/"
    },
    {
        "website": "https://peraturan.bpk.go.id/"
    },
    {
        "website": "https://lindungihakpilihmu.kpu.go.id/"
    },
    {
        "website": "https://pmprb.menpan.go.id/"
    },
    {
        "website": "https://lpse.kemenag.go.id/"
    },
    {
        "website": "https://lpse.lampungprov.go.id/"
    },
    {
        "website": "https://dpmptsp.cianjurkab.go.id/"
    },
    {
        "website": "https://disperkimlh.kebumenkab.go.id/"
    },
    {
        "website": "https://dpupr.blitarkab.go.id/"
    },
    {
        "website": "https://lpse.banyuwangikab.go.id/"
    },
    {
        "website": "https://buleleng.bulelengkab.go.id/"
    },
    {
        "website": "https://pip.kemdikbud.go.id/"
    },
    {
        "website": "https://putusan3.mahkamahagung.go.id/"
    },
    {
        "website": "https://sipp.pn-tarakan.go.id/"
    },
    {
        "website": "https://jdih.kemenkeu.go.id/"
    },
    {
        "website": "https://www.tekmira.esdm.go.id/"
    },
    {
        "website": "https://dkp.kaltimprov.go.id/"
    },
    {
        "website": "https://web.karokab.go.id/"
    },
    {
        "website": "https://diperpautkan.bantulkab.go.id/"
    },
    {
        "website": "https://dinkes.bantenprov.go.id/"
    },
    {
        "website": "https://pariwisata.demakkab.go.id/"
    },
    {
        "website": "https://pse.kominfo.go.id/"
    },
    {
        "website": "https://asn-unggul.lan.go.id/"
    },
    {
        "website": "https://www.bpip.go.id/"
    },
    {
        "website": "https://bulungan.go.id/"
    },
    {
        "website": "https://lampungbaratkab.go.id/"
    },
    {
        "website": "https://lampungutarakab.go.id/"
    },
    {
        "website": "https://www.jembranakab.go.id/"
    },
    {
        "website": "https://www.magetan.go.id/"
    },
    {
        "website": "https://niasbaratkab.go.id/"
    },
    {
        "website": "https://jdih.kominfo.go.id/"
    },
    {
        "website": "https://mojokertokota.go.id/"
    },
    {
        "website": "https://www.lumajangkab.go.id/"
    },
    {
        "website": "https://gunungmaskab.go.id/"
    },
    {
        "website": "https://sibamas.tangerangkab.go.id/"
    },
    {
        "website": "https://beraukab.go.id/"
    },
    {
        "website": "https://www.rejanglebongkab.go.id/"
    },
    {
        "website": "https://kalteng.go.id/"
    },
    {
        "website": "https://dpmpt.pasuruankab.go.id/"
    },
    {
        "website": "https://gumaskab.bps.go.id/"
    },
    {
        "website": "https://covid19.kuningankab.go.id/"
    },
    {
        "website": "https://diskominfo.karanganyarkab.go.id/"
    },
    {
        "website": "https://enrekangkab.go.id/"
    },
    {
        "website": "https://dispermadesdukcapil.jatengprov.go.id/"
    },
    {
        "website": "https://kesehatan.jogjakota.go.id/"
    },
    {
        "website": "https://lpse.tangerangselatankota.go.id/"
    },
    {
        "website": "https://kejari-badung.go.id/"
    },
    {
        "website": "https://sulut.kemenag.go.id/"
    },
    {
        "website": "https://bctemas.beacukai.go.id/"
    },
    {
        "website": "https://humas.paserkab.go.id/"
    },
    {
        "website": "https://www.pn-cikarang.go.id/"
    },
    {
        "website": "https://simlitabmas.ristekbrin.go.id/"
    },
    {
        "website": "https://www.tanggamus.go.id/"
    },
    {
        "website": "https://mesujikab.go.id/"
    },
    {
        "website": "https://pa-kualakurun.go.id/"
    },
    {
        "website": "https://halomasbup.kedirikab.go.id/"
    },
    {
        "website": "https://infoloker.karawangkab.go.id/"
    },
    {
        "website": "https://konsultan.pajak.go.id/"
    },
    {
        "website": "https://www.bpjsketenagakerjaan.go.id/"
    },
    {
        "website": "https://www.nganjukkab.go.id/"
    },
    {
        "website": "https://jdih.bapeten.go.id/"
    },
    {
        "website": "https://diskominfo.kuburayakab.go.id/"
    },
    {
        "website": "https://dki.kemenag.go.id/"
    },
    {
        "website": "https://ksm.kemenag.go.id/"
    },
    {
        "website": "https://diskominfo.mataramkota.go.id/"
    },
    {
        "website": "https://arpus.acehprov.go.id/"
    },
    {
        "website": "https://dinkes.kotaprabumulih.go.id/"
    },
    {
        "website": "https://bkd.kalteng.go.id/"
    },
    {
        "website": "https://lpse.slemankab.go.id/"
    },
    {
        "website": "https://disdik.sinjaikab.go.id/"
    },
    {
        "website": "https://sehatnegeriku.kemkes.go.id/"
    }
]